<?xml version="1.0" encoding="utf-8"?>
<ProductInfo>
  <product>
    <title>3D Pen Black &amp;amp; 15 Colors Filament</title>
    <brand>ccbetter&amp;reg;</brand>
    <url>http://www.amazon.com/ccbetter-Intelligent-Printing-Filament-Version/dp/B01B5YGS0U/ref=sr_1_241/185-6656338-1956833?s=industrial&amp;ie=UTF8&amp;qid=1460819356&amp;sr=1-241</url>
  </product>
<product><title>3D Pen Black &amp;amp; 15 Colors Filament</title><brand>ccbetter&amp;reg;</brand><url>http://www.amazon.com/ccbetter-Intelligent-Printing-Filament-Version/dp/B01B5YGS0U/ref=sr_1_5453/189-2143890-5707160?s=industrial&amp;ie=UTF8&amp;qid=1460825715&amp;sr=1-5453</url></product></ProductInfo>
