<?xml version="1.0" encoding="utf-8"?>
<ProductInfo>
  <product>
    <title>3mm ABS blue Filament 1.5kg (=3.306 lbs) On Spool for 3D Printer MakerBot, RepRap, MakeGear &amp;amp; Up!</title>
    <brand>Unknown</brand>
    <url>http://www.amazon.com/ABS-Filament-Printer-MakerBot-MakeGear/dp/B00884LDY2/ref=sr_1_551/177-3047050-0862645?s=industrial&amp;ie=UTF8&amp;qid=1460819732&amp;sr=1-551</url>
  </product>
<product><title>Jet- ABS (3mm, Green color, 1.0kg =2.205 lbs) Filament on Spool for 3D Printer MakerBot RepRap and UP!</title><brand>Unknown</brand><url>http://www.amazon.com/ABS-Filament-Printer-MakerBot-RepRap/dp/B00815RK9U/ref=sr_1_1490/186-2865094-8538756?s=industrial&amp;ie=UTF8&amp;qid=1460820911&amp;sr=1-1490</url></product><product><title>Jet- ABS (3mm, Gold color, 1.0kg =2.204 lbs) Filament On Spool for 3D Printer MakerBot, RepRap, MakerGear, Ultimaker...</title><brand>Unknown</brand><url>http://www.amazon.com/ABS-Filament-MakerBot-MakerGear-Ultimaker/dp/B00815L816/ref=sr_1_1499/186-2865094-8538756?s=industrial&amp;ie=UTF8&amp;qid=1460820911&amp;sr=1-1499</url></product><product><title>Jet - ABS (3mm, Red color, 1.0kg =2.204lbs) Filament on Spool for 3D Printer MakerBot, RepRap, MakerGear, Ultimaker...</title><brand>Unknown</brand><url>http://www.amazon.com/Jet-2-204lbs-Filament-MakerGear-Ultimaker/dp/B00815MUL8/ref=sr_1_1613/184-3955035-0226812?s=industrial&amp;ie=UTF8&amp;qid=1460821049&amp;sr=1-1613</url></product><product><title>Jet - ABS (1.75mm, Natural color, 1.0kg =2.204lbs) Filament on Spool for 3D Printer MakerBot, RepRap, MakerGear...</title><brand>Unknown</brand><url>http://www.amazon.com/Jet-2-204lbs-Filament-MakerGear-Ultimaker/dp/B007M0JHVO/ref=sr_1_3334/184-1020677-9160061?s=industrial&amp;ie=UTF8&amp;qid=1460823135&amp;sr=1-3334</url></product><product><title>Jet - ABS (3mm, Natural color, 1.0kg =2.204lbs) Filament on Spool for 3D Printer MakerBot, RepRap, MakerGear,...</title><brand>Unknown</brand><url>http://www.amazon.com/Jet-2-204lbs-Filament-MakerGear-Ultimaker/dp/B007M0JMHS/ref=sr_1_3473/175-6648558-5604522?s=industrial&amp;ie=UTF8&amp;qid=1460823316&amp;sr=1-3473</url></product><product><title>Jet- ABS (1.75mm, Gold color, 1.0kg =2.204 lbs) Filament On Spool for 3D Printer MakerBot, RepRap, MakerGear,...</title><brand>Unknown</brand><url>http://www.amazon.com/ABS-Filament-MakerBot-MakerGear-Ultimaker/dp/B007R55CB8/ref=sr_1_3639/192-1505291-6532509?s=industrial&amp;ie=UTF8&amp;qid=1460823511&amp;sr=1-3639</url></product><product><title>Jet- ABS (1.75mm, Pink color, 1.0kg =2.204 lbs) Filament On Spool for 3D Printer MakerBot, RepRap, MakerGear,...</title><brand>Unknown</brand><url>http://www.amazon.com/ABS-Filament-MakerBot-MakerGear-Ultimaker/dp/B0085R0J6A/ref=sr_1_3646/192-1505291-6532509?s=industrial&amp;ie=UTF8&amp;qid=1460823511&amp;sr=1-3646</url></product><product><title>Jet- ABS (3mm, Grey color, 1.0kg =2.204 lbs) Filament On Spool for 3D Printer MakerBot, RepRap, MakerGear, Ultimaker...</title><brand>Unknown</brand><url>http://www.amazon.com/ABS-Filament-MakerBot-MakerGear-Ultimaker/dp/B007R56FGY/ref=sr_1_3701/181-5879015-2942914?s=industrial&amp;ie=UTF8&amp;qid=1460823596&amp;sr=1-3701</url></product><product><title>Jet- ABS (1.75mm, Silver color, 1.0kg =2.204 lbs) Filament On Spool for 3D Printer MakerBot, RepRap, MakerGear...</title><brand>Unknown</brand><url>http://www.amazon.com/ABS-Filament-MakerBot-MakerGear-Ultimaker/dp/B007R540FM/ref=sr_1_3723/187-8707605-7251468?s=industrial&amp;ie=UTF8&amp;qid=1460823614&amp;sr=1-3723</url></product><product><title>Jet - ABS (1.75mm, Orange color, 1.0kg =2.204lbs) Filament on Spool for 3D Printer MakerBot, RepRap, MakerGear...</title><brand>Unknown</brand><url>http://www.amazon.com/Jet-2-204lbs-Filament-MakerGear-Ultimaker/dp/B007R4X9YG/ref=sr_1_3736/175-9816791-2841455?s=industrial&amp;ie=UTF8&amp;qid=1460823633&amp;sr=1-3736</url></product><product><title>Jet - ABS (1.75mm, Green color, 1.3 kg =2.86lbs) Filament on Spool for 3D Printer MakerBot, RepRap, MakerGear,...</title><brand>Unknown</brand><url>http://www.amazon.com/Jet-Filament-MakerBot-MakerGear-Ultimaker/dp/B008GE36BM/ref=sr_1_3809/183-6918856-5598252?s=industrial&amp;ie=UTF8&amp;qid=1460823727&amp;sr=1-3809</url></product><product><title>Jet - ABS (1.75mm, Orange color, 1.0kg =2.204lbs) Filament on Spool for 3D Printer MakerBot, RepRap, MakerGear...</title><brand>Unknown</brand><url>http://www.amazon.com/Jet-2-204lbs-Filament-MakerGear-Ultimaker/dp/B007R4X9YG/ref=sr_1_3815/183-6918856-5598252?s=industrial&amp;ie=UTF8&amp;qid=1460823727&amp;sr=1-3815</url></product><product><title>Jet- ABS (1.75mm, Gold color, 1.0kg =2.204 lbs) Filament On Spool for 3D Printer MakerBot, RepRap, MakerGear,...</title><brand>Unknown</brand><url>http://www.amazon.com/ABS-Filament-MakerBot-MakerGear-Ultimaker/dp/B007R55CB8/ref=sr_1_3817/183-6918856-5598252?s=industrial&amp;ie=UTF8&amp;qid=1460823727&amp;sr=1-3817</url></product><product><title>Jet - ABS (3mm, Blue color, 1.0kg =2.204 lbs) Filament on Spool for 3D Printer MakerBot, RepRap, MakerGear, Ultimaker...</title><brand>Unknown</brand><url>http://www.amazon.com/Jet-Filament-MakerBot-MakerGear-Ultimaker/dp/B007R524D2/ref=sr_1_3901/188-3947044-1074751?s=industrial&amp;ie=UTF8&amp;qid=1460823820&amp;sr=1-3901</url></product><product><title>Jet- ABS (1.75mm, Yellow color, 1.0kg =2.205 lbs) Filament on Spool for 3D Printer MakerBot, RepRap, MakerGear...</title><brand>Unknown</brand><url>http://www.amazon.com/ABS-Filament-MakerBot-MakerGear-Ultimaker/dp/B007M0J4HG/ref=sr_1_4140/179-5101271-4485450?s=industrial&amp;ie=UTF8&amp;qid=1460824109&amp;sr=1-4140</url></product><product><title>1.75mm ABS Yellow Filament 1.3kg (=2.86 lbs) On Spool for 3D Printer MakerBot, RepRap, MakeGear &amp;amp; Up!</title><brand>Unknown</brand><url>http://www.amazon.com/ABS-Filament-Printer-MakerBot-MakeGear/dp/B00884FPUA/ref=sr_1_4155/191-0009108-0043575?s=industrial&amp;ie=UTF8&amp;qid=1460824127&amp;sr=1-4155</url></product><product><title>Jet- ABS (1.75mm, Yellow color, 1.0kg =2.205 lbs) Filament on Spool for 3D Printer MakerBot, RepRap, MakerGear...</title><brand>Unknown</brand><url>http://www.amazon.com/ABS-Filament-MakerBot-MakerGear-Ultimaker/dp/B007M0J4HG/ref=sr_1_4170/184-7933710-6799325?s=industrial&amp;ie=UTF8&amp;qid=1460824146&amp;sr=1-4170</url></product><product><title>Jet - ABS (3mm, Purple color, 1.0kg =2.204lbs) Filament on Spool for 3D Printer MakerBot, RepRap, MakerGear, Ultimaker...</title><brand>Unknown</brand><url>http://www.amazon.com/Jet-2-204lbs-Filament-MakerGear-Ultimaker/dp/B007R4UCUU/ref=sr_1_4424/175-3321425-3811434?s=industrial&amp;ie=UTF8&amp;qid=1460824448&amp;sr=1-4424</url></product><product><title>Jet- ABS (3mm, Yellow color, 1.0kg =2.205 lbs) Filament on Spool for 3D Printer MakerBot, RepRap, MakerGear, Ultimaker...</title><brand>Unknown</brand><url>http://www.amazon.com/ABS-Filament-MakerBot-MakerGear-Ultimaker/dp/B007M0J6RE/ref=sr_1_4743/182-3140281-4154214?s=industrial&amp;ie=UTF8&amp;qid=1460824843&amp;sr=1-4743</url></product><product><title>Jet- ABS (1.75mm, Pink color, 1.3kg =2.86 lbs) Filament On Spool for 3D Printer MakerBot, RepRap, MakerGear, Ultimaker...</title><brand>Unknown</brand><url>http://www.amazon.com/ABS-Filament-MakerBot-MakerGear-Ultimaker/dp/B008GE4CZQ/ref=sr_1_4809/182-6127799-2820037?s=industrial&amp;ie=UTF8&amp;qid=1460824924&amp;sr=1-4809</url></product><product><title>Jet- PLA (3mm, Pink color, 1.0kg =2.204 lbs) Filament On Spool for 3D Printer MakerBot, RepRap, MakerGear, Ultimaker...</title><brand>Unknown</brand><url>http://www.amazon.com/Filament-Printer-MakerBot-MakerGear-Ultimaker/dp/B0085R1A36/ref=sr_1_5623/185-6805669-2387701?s=industrial&amp;ie=UTF8&amp;qid=1460825934&amp;sr=1-5623</url></product><product><title>3mm ABS Green Glow in Dark Filament 1.0kg (=2.205 lbs) on Spool for 3D Printer MakerBot RepRap and UP! -Jet</title><brand>Unknown</brand><url>http://www.amazon.com/ABS-Filament-Printer-MakerBot-RepRap/dp/B008C3DKOK/ref=sr_1_5660/176-4005261-3550042?s=industrial&amp;ie=UTF8&amp;qid=1460825971&amp;sr=1-5660</url></product><product><title>Jet - PLA (3mm, Red color, 1.0kg =2.204lbs) Filament on Spool for 3D Printer MakerBot, RepRap, MakerGear, Ultimaker...</title><brand>Unknown</brand><url>http://www.amazon.com/Jet-2-204lbs-Filament-MakerGear-Ultimaker/dp/B008184S4W/ref=sr_1_5833/186-6413115-7010014?s=industrial&amp;ie=UTF8&amp;qid=1460826189&amp;sr=1-5833</url></product><product><title>Jet - ABS (1.75mm, Clear color Transparent, 1.0kg =2.204lbs) Filament on Spool for 3D Printer MakerBot, RepRap...</title><brand>Unknown</brand><url>http://www.amazon.com/Jet-Transparent-2-204lbs-MakerGear-Ultimaker/dp/B00ATR2E76/ref=sr_1_5965/191-8873176-7906843?s=industrial&amp;ie=UTF8&amp;qid=1460826338&amp;sr=1-5965</url></product><product><title>Jet - PLA (3mm, Orange color, 1.0kg =2.204lbs) Filament on Spool for 3D Printer MakerBot, RepRap, MakerGear, Ultimaker...</title><brand>Unknown</brand><url>http://www.amazon.com/Jet-2-204lbs-Filament-MakerGear-Ultimaker/dp/B007R4XSFQ/ref=sr_1_6087/180-2397481-3861251?s=industrial&amp;ie=UTF8&amp;qid=1460826496&amp;sr=1-6087</url></product><product><title>Jet- PLA (3mm, Yellow color, 1.0kg =2.205 lbs) Filament on Spool for 3D Printer MakerBot, RepRap, MakerGear, Ultimaker...</title><brand>Unknown</brand><url>http://www.amazon.com/PLA-Filament-MakerBot-MakerGear-Ultimaker/dp/B007O340JS/ref=sr_1_6124/183-9594290-0295146?s=industrial&amp;ie=UTF8&amp;qid=1460826539&amp;sr=1-6124</url></product></ProductInfo>
